cyjax/__init__.py
cyjax/api_client.py
cyjax/exceptions.py
cyjax/helpers.py
cyjax/types.py
cyjax/resources/__init__.py
cyjax/resources/model_dto.py
cyjax/resources/resource.py
cyjax/resources/case_management/__init__.py
cyjax/resources/case_management/dto.py
cyjax/resources/case_management/resource.py
cyjax/resources/dashboard/__init__.py
cyjax/resources/dashboard/dto.py
cyjax/resources/dashboard/resource.py
cyjax/resources/data_breach/__init__.py
cyjax/resources/data_breach/dto.py
cyjax/resources/data_breach/leaked_email.py
cyjax/resources/data_breach/resource.py
cyjax/resources/incident_report/__init__.py
cyjax/resources/incident_report/dto.py
cyjax/resources/incident_report/resource.py
cyjax/resources/indicator_of_compromise/__init__.py
cyjax/resources/indicator_of_compromise/dto.py
cyjax/resources/indicator_of_compromise/resource.py
cyjax/resources/malicious_domain/__init__.py
cyjax/resources/malicious_domain/dto.py
cyjax/resources/malicious_domain/resource.py
cyjax/resources/paste/__init__.py
cyjax/resources/paste/dto.py
cyjax/resources/paste/resource.py
cyjax/resources/social_media/__init__.py
cyjax/resources/social_media/dto.py
cyjax/resources/social_media/resource.py
cyjax/resources/tailored_report/__init__.py
cyjax/resources/tailored_report/dto.py
cyjax/resources/tailored_report/resource.py
cyjax/resources/third_party_risk/__init__.py
cyjax/resources/third_party_risk/dto.py
cyjax/resources/third_party_risk/supplier.py
cyjax/resources/third_party_risk/tier.py
cyjax/resources/threat_actor/__init__.py
cyjax/resources/threat_actor/dto.py
cyjax/resources/threat_actor/resource.py
cyjax/resources/tor_exit_node/__init__.py
cyjax/resources/tor_exit_node/dto.py
cyjax/resources/tor_exit_node/resource.py
cyjax/resources/tweet/__init__.py
cyjax/resources/tweet/dto.py
cyjax/resources/tweet/resource.py
test/__init__.py
test/api_client_test.py
test/case_management_test.py
test/dashboard_test.py
test/data_breach_test.py
test/data_leak_test.py
test/date_helper_test.py
cyjax_cti-2.1.0.dist-info/LICENSE
cyjax_cti-2.1.0.dist-info/METADATA
cyjax_cti-2.1.0.dist-info/WHEEL
cyjax_cti-2.1.0.dist-info/top_level.txt
cyjax_cti-2.1.0.dist-info/RECORD
