Metadata-Version: 2.1
Name: cyjax-cti
Version: 2.1.0
Summary: cyjax-cti provides a Python library to use Cyjax platform API.
Home-page: https://www.cyjax.com
Author: Cyjax Ltd.
Author-email: github@cyjax.com
License: MIT
Platform: UNKNOWN
Classifier: Development Status :: 5 - Production/Stable
Classifier: Environment :: Web Environment
Classifier: Intended Audience :: Developers
Classifier: License :: OSI Approved :: MIT License
Classifier: Operating System :: OS Independent
Classifier: Programming Language :: Python
Classifier: Programming Language :: Python :: 3
Classifier: Programming Language :: Python :: 3.6
Classifier: Programming Language :: Python :: 3.7
Classifier: Programming Language :: Python :: 3.8
Classifier: Programming Language :: Python :: 3.9
Classifier: Topic :: Software Development
Requires-Python: >=3.6
License-File: LICENSE
Requires-Dist: requests (<3,>=2.27.0)
Requires-Dist: pytz (<2024,>=2023.3)
Provides-Extra: test
Requires-Dist: pytest ; extra == 'test'
Requires-Dist: pytest-mock ; extra == 'test'
Requires-Dist: responses (==0.17) ; extra == 'test'
Requires-Dist: twine ; extra == 'test'
Requires-Dist: flake8 ; extra == 'test'
